{"tree_1038.md":"0489e72c","tree_105.md":"4c017fb9","tree_226.md":"57125b22","advanced-algo_bit.md":"5cb8064e","advanced-algo_union-find.md":"21705499","bits_371.md":"cb4561bb","bits_intro.md":"2a0a2ac7","contribute.md":"8a688296","dfs_2385.md":"cff49075","dfs_695.md":"2f6b6d20","dynamic-programming_300.md":"901d6da5","dynamic-programming_376.md":"205ea6c8","dynamic-programming_5.md":"a39dc11b","dynamic-programming_509.md":"ccf0170e","dynamic-programming_576.md":"6138ccfa","dynamic-programming_85.md":"a1d1073e","dynamic-programming_91.md":"edc08198","dynamic-programming_dp-intro.md":"54f48887","getting-started.md":"9472b5e9","hash-table_1074.md":"edec34de","hash-table_560.md":"5bdee690","hash-table_659.md":"59bb14ce","index.md":"3b655c5e","introduction_index.md":"775dca41","sort_merge-sort.md":"ee94adb9","sort_topological-sort.md":"44959f3d","stack_2350.md":"2d72d11d","string_13.md":"8349c508","string_792.md":"f80ab6a3","table-of-content.md":"be7fdcb8"}
