{"tree_226.md":"4afa25f9","tree_105.md":"0d0e8152","tree_bt-iterative-traversal.md":"1ab1166f","tree_1038.md":"f29ffef2","bits_371.md":"a2912555","tree_red-black.md":"6ecd7a01","tree_minimum-spanning-tree.md":"3665624e","dynamic-programming_5.md":"825d563c","dynamic-programming_85.md":"d1244dbf","bits_intro.md":"406ecce5","dynamic-programming_509.md":"a191bbee","contribute.md":"344150f4","string_13.md":"ce09ea59","dynamic-programming_376.md":"b55e5c8f","advanced-algo_bit.md":"63ad1f55","getting-started.md":"06ba29f8","hash-table_659.md":"f6bcecb8","introduction_index.md":"972b72f0","hash-table_560.md":"cb8f2600","index.md":"f7ccd87e","dynamic-programming_dp-intro.md":"f0ee5300","advanced-algo_union-find.md":"c49a24ef","dynamic-programming_91.md":"002296d7","hash-table_1074.md":"01005839","sort_quick-sort.md":"81250dec","table-of-content.md":"c43e1167","stack_2350.md":"a972b583","string_kmp.md":"75625b40","dynamic-programming_1312.md":"b2df6302","dfs_695.md":"5d31a92b","string_792.md":"4f95df04","dynamic-programming_300.md":"7e794041","dynamic-programming_576.md":"9d68eeac","sort_merge-sort.md":"dba378d8","tree_trie.md":"a93937ed","sort_topological-sort.md":"d90012a8","dfs_2385.md":"0d4ead45"}
